dotbot_windows.py
dotbot_windows-1.1.0.dist-info/LICENSE.txt
dotbot_windows-1.1.0.dist-info/METADATA
dotbot_windows-1.1.0.dist-info/WHEEL
dotbot_windows-1.1.0.dist-info/RECORD
