Metadata-Version: 2.1
Name: dotbot-windows
Version: 1.1.0
Summary: Configure Windows using dotbot
Home-page: https://github.com/kurtmckee/dotbot-windows
License: MIT
Keywords: dotbot,dotbot-plugin,windows,dotfiles
Author: Kurt McKee
Author-email: contactme@kurtmckee.org
Requires-Python: >=3.8
Classifier: License :: OSI Approved :: MIT License
Classifier: Programming Language :: Python :: 3
Classifier: Programming Language :: Python :: 3.8
Classifier: Programming Language :: Python :: 3.9
Classifier: Programming Language :: Python :: 3.10
Classifier: Programming Language :: Python :: 3.11
Classifier: Programming Language :: Python :: 3.12
Requires-Dist: dotbot (>=1.20.1)
Project-URL: Repository, https://github.com/kurtmckee/dotbot-windows
